{"cameraMode":{"drawMode":0,"name":"Shaded","section":"Shading Mode"},"sceneLighting":false,"audioPlay":false,"sceneViewState":{"showFog":true,"showMaterialUpdate":false,"showSkybox":false,"showFlares":true,"showImageEffects":true,"showParticleSystems":true},"in2DMode":false,"pivot":{"x":0.021682053804397584,"y":0.14081799983978272,"z":0.0079708993434906},"rotation":{"x":0.19484631717205048,"y":0.7222996950149536,"z":-0.22725994884967805,"w":0.6240024566650391},"size":1.3823175430297852,"orthographic":false}